MANIFEST.in
README.txt
requirements.txt
setup.py
test_requirements.txt
version.txt
cloudshell/__init__.py
cloudshell/core/__init__.py
cloudshell/core/driver_request.py
cloudshell/core/driver_response.py
cloudshell/core/driver_response_root.py
cloudshell/core/context/__init__.py
cloudshell/core/context/error_handling_context.py
cloudshell/core/logger/__init__.py
cloudshell/core/logger/interprocess_logger.py
cloudshell/core/logger/qs_config.ini
cloudshell/core/logger/qs_config_parser.py
cloudshell/core/logger/qs_logger.py
cloudshell_core.egg-info/PKG-INFO
cloudshell_core.egg-info/SOURCES.txt
cloudshell_core.egg-info/dependency_links.txt
cloudshell_core.egg-info/top_level.txt
tests/__init__.py
tests/cloudshell_core_tests.py
tests/core/__init__.py
tests/core/logger/__init__.py
tests/core/logger/test_qs_config_parser.py
tests/core/logger/test_qs_logger.py
tests/core/logger/config/test_qs_config.ini